hal9k_api/__main__.py
hal9k_api/api.py
hal9k_api/const.py
Hal9k_API-0.1.2.dist-info/LICENSE
Hal9k_API-0.1.2.dist-info/METADATA
Hal9k_API-0.1.2.dist-info/WHEEL
Hal9k_API-0.1.2.dist-info/top_level.txt
Hal9k_API-0.1.2.dist-info/RECORD
