Metadata-Version: 2.1
Name: Hal9k-API
Version: 0.1.2
Summary: The HackerLab 9000 API Server.
Home-page: https://github.com/haxys-labs/Hal9k-Overmind-API
Author: CMSteffen
Author-email: cmsteffen@haxys.net
License: MIT
Project-URL: Source Code, https://github.com/haxys-labs/Hal9k-Overmind-API
Project-URL: Documentation, https://github.com/haxys-labs/Hal9k-Overmind-API
Keywords: hacker hacking lab laboratory virtual machine virtualbox vm flask
Platform: UNKNOWN
Classifier: Development Status :: 2 - Pre-Alpha
Classifier: Environment :: Console
Classifier: Environment :: Web Environment
Classifier: Framework :: Flask
Classifier: Intended Audience :: Developers
Classifier: Intended Audience :: System Administrators
Classifier: License :: OSI Approved :: MIT License
Classifier: Natural Language :: English
Classifier: Operating System :: POSIX :: Linux
Classifier: Programming Language :: Python :: 3
Classifier: Programming Language :: Python :: 3.6
Classifier: Programming Language :: Python :: 3.7
Classifier: Programming Language :: Python :: 3.8
Classifier: Programming Language :: Python :: 3.9
Classifier: Topic :: Internet
Classifier: Topic :: Internet :: WWW/HTTP
Classifier: Topic :: Internet :: WWW/HTTP :: WSGI
Classifier: Topic :: Internet :: WWW/HTTP :: WSGI :: Server
Classifier: Topic :: Security
Classifier: Topic :: System
Classifier: Topic :: System :: Networking
Classifier: Topic :: System :: Systems Administration
Classifier: Topic :: Utilities
Requires-Dist: Lib-Hal9k (>=0.7.0)
Requires-Dist: flask (>=1.1.2)
Requires-Dist: flask-cors (>=3.0.8)
